aot/LICENSE
aot/README.md
aot/__init__.py
aot/configs/__init__.py
aot/configs/default.py
aot/configs/pre.py
aot/configs/pre_dav.py
aot/configs/pre_ytb.py
aot/configs/pre_ytb_dav.py
aot/configs/swinb_pre_ytb_dav_mose_vip_ovis_got_lasot.py
aot/configs/ytb.py
aot/configs/models/aotb.py
aot/configs/models/aotl.py
aot/configs/models/aots.py
aot/configs/models/aott.py
aot/configs/models/deaotb.py
aot/configs/models/deaotl.py
aot/configs/models/deaots.py
aot/configs/models/deaott.py
aot/configs/models/default.py
aot/configs/models/default_deaot.py
aot/configs/models/r101_aotl.py
aot/configs/models/r50_aotl.py
aot/configs/models/r50_deaotl.py
aot/configs/models/r50_dm_aotl.py
aot/configs/models/r50_dm_deaotl.py
aot/configs/models/rs101_aotl.py
aot/configs/models/swinb_aotl.py
aot/configs/models/swinb_deaotl.py
aot/configs/models/swinb_dm_aotl.py
aot/configs/models/swinb_dm_deaotl.py
aot/dataloaders/__init__.py
aot/dataloaders/eval_datasets.py
aot/dataloaders/image_transforms.py
aot/dataloaders/train_datasets.py
aot/dataloaders/video_transforms.py
aot/networks/__init__.py
aot/networks/decoders/__init__.py
aot/networks/decoders/fpn.py
aot/networks/encoders/__init__.py
aot/networks/encoders/mobilenetv2.py
aot/networks/encoders/mobilenetv3.py
aot/networks/encoders/resnet.py
aot/networks/encoders/resnest/__init__.py
aot/networks/encoders/resnest/resnest.py
aot/networks/encoders/resnest/resnet.py
aot/networks/encoders/resnest/splat.py
aot/networks/encoders/swin/__init__.py
aot/networks/encoders/swin/build.py
aot/networks/encoders/swin/swin_transformer.py
aot/networks/engines/__init__.py
aot/networks/engines/aot_engine.py
aot/networks/engines/deaot_engine.py
aot/networks/engines/dm_aot_engine.py
aot/networks/engines/dm_deaot_engine.py
aot/networks/layers/__init__.py
aot/networks/layers/attention.py
aot/networks/layers/basic.py
aot/networks/layers/loss.py
aot/networks/layers/normalization.py
aot/networks/layers/position.py
aot/networks/layers/transformer.py
deaotpy-1.11.0.dist-info/LICENSE
deaotpy-1.11.0.dist-info/METADATA
deaotpy-1.11.0.dist-info/WHEEL
deaotpy-1.11.0.dist-info/top_level.txt
deaotpy-1.11.0.dist-info/RECORD
