Metadata-Version: 2.1
Name: deaotpy
Version: 1.11.0
Summary: Decoupling Features in Hierarchical Propagation for Video Object Segmentation.
License: BSD 3-Clause License
Project-URL: repository, https://github.com/yoxu515/aot-benchmark
Keywords: deep-learning,pytorch,vision,object-segmentation,video
Classifier: Development Status :: 5 - Production/Stable
Classifier: Operating System :: OS Independent
Classifier: Intended Audience :: Science/Research
Classifier: Programming Language :: Python :: 3
Classifier: License :: OSI Approved :: BSD License
Classifier: Topic :: Scientific/Engineering :: Artificial Intelligence
Requires-Python: >=3.10
License-File: LICENSE
Requires-Dist: numpy >=1.23.5
Requires-Dist: torch >=2.0.0
Requires-Dist: torchvision >=0.15.1
Requires-Dist: spatial-correlation-sampler >=0.4.0
